[
  {
    "label": "Action",
    "category": "action",
    "items": [
      "add",
      "add-card",
      "auto-login",
      "backspace",
      "changelog",
      "circle-add",
      "circle-close",
      "close",
      "copy-paste",
      "cut-paste",
      "disabled-microphone",
      "download",
      "drag-and-drop",
      "edit",
      "fast-forward",
      "favorite",
      "filter",
      "forward",
      "full-screen",
      "hide-password",
      "indeterminate",
      "install",
      "link",
      "logout",
      "loop",
      "menu",
      "microphone",
      "minimize-screen",
      "more",
      "move",
      "mute",
      "notification",
      "pause",
      "pin",
      "play",
      "pop-up-window",
      "print",
      "random",
      "refresh",
      "remove",
      "restart",
      "search",
      "shopping-cart",
      "show-password",
      "sort",
      "sound-on",
      "stream-on",
      "success",
      "thumbs-down",
      "thumbs-up",
      "tiles-add",
      "upload",
      "volume-down",
      "volume-up",
      "zoom-in",
      "zoom-out"
    ]
  },
  {
    "label": "Alert",
    "category": "alert",
    "items": [
      "compliance",
      "error",
      "help",
      "imprint-dataprivacy",
      "information",
      "legal",
      "security",
      "success",
      "warning"
    ]
  },
  {
    "label": "Communication",
    "category": "communication",
    "items": [
      "call-incoming",
      "call-outgoing",
      "chat",
      "email",
      "end-call",
      "feedback",
      "message",
      "phone-number",
      "recipient",
      "voice-message"
    ]
  },
  {
    "label": "Content",
    "category": "content",
    "items": [
      "achievement",
      "applications",
      "biometric",
      "bookmark",
      "calendar",
      "clipboard",
      "clock",
      "credit-card",
      "delivery",
      "digital-banking",
      "digital-media",
      "draft-file",
      "e-sim",
      "eu",
      "features",
      "flexible-tariffs",
      "heart",
      "history",
      "international",
      "international-sms",
      "interview",
      "key",
      "lock",
      "media-folder",
      "money-at",
      "music",
      "news",
      "prepaid-activate",
      "price-tag",
      "rss",
      "shop",
      "signal",
      "sim-card",
      "smile",
      "tariffs",
      "transport",
      "unlock",
      "voucher",
      "wallet"
    ]
  },
  {
    "label": "Device",
    "category": "device",
    "items": [
      "add-device",
      "camera",
      "change-camera",
      "computer",
      "device-phone",
      "device-router",
      "device-tv",
      "device-watch",
      "fixed-line-services",
      "media-receiver",
      "mobile-devices-combination",
      "mobile-equipment",
      "mobile-phone-insurance",
      "mobile-services",
      "no-camera",
      "photo-camera",
      "remote-controller",
      "replacement-mobilephone",
      "screen-rotate",
      "smart-speaker",
      "tv-and-mobile"
    ]
  },
  {
    "label": "Home",
    "category": "home",
    "items": [
      "home",
      "internet-at-home",
      "iot",
      "no-wifi",
      "smarthome",
      "wifi"
    ]
  },
  {
    "label": "Navigation",
    "category": "navigation",
    "items": [
      "circle-top-up",
      "collapse-down",
      "collapse-up",
      "external-link",
      "internal-link",
      "left",
      "location",
      "my-location",
      "right",
      "start",
      "top-up"
    ]
  },
  {
    "label": "Process",
    "category": "process",
    "items": [
      "order-status",
      "processing"
    ]
  },
  {
    "label": "Service",
    "category": "service",
    "items": [
      "devices-service",
      "maintanance",
      "services",
      "settings",
      "support"
    ]
  },
  {
    "label": "T Product",
    "category": "t-product",
    "items": [
      "magenta-cloud",
      "magenta-tv",
      "magentaone",
      "measure-internet-speed",
      "seamless-connectivity",
      "telekom-shop-b",
      "usage"
    ]
  },
  {
    "label": "User File",
    "category": "user-file",
    "items": [
      "analytics",
      "attachment",
      "audio-file",
      "billing",
      "bussines-users",
      "communities",
      "contacts",
      "contracts",
      "families",
      "handshake",
      "id-card",
      "image-file",
      "logout",
      "pdf-file",
      "switch-users",
      "user",
      "videos"
    ]
  },
  {
    "label": "Weather",
    "category": "weather",
    "items": [
      "cloudy",
      "cloudy-rain",
      "cloudy-sleet",
      "cloudy-snow",
      "cloudy-thunder-rain",
      "cloudy-thunder-snow",
      "heavy-sleet",
      "heavy-snow",
      "moon-clear",
      "moon-cloudy-a",
      "moon-cloudy-b",
      "moon-rain",
      "moon-sleet",
      "moon-snow",
      "moon-thunder-rain",
      "moon-thunder-snow",
      "overcast",
      "rain",
      "sunny",
      "thunder-rain",
      "thunder-snow"
    ]
  }
]